{"cameraMode":{"drawMode":0,"name":"Shaded","section":"Shading Mode"},"sceneLighting":true,"audioPlay":false,"sceneViewState":{"m_AlwaysRefresh":false,"showFog":true,"showSkybox":true,"showFlares":true,"showImageEffects":true,"showParticleSystems":true,"showVisualEffectGraphs":true,"m_FxEnabled":true},"in2DMode":false,"pivot":{"x":45.24980926513672,"y":16.895389556884767,"z":-102.5833740234375},"rotation":{"x":0.18175575137138368,"y":-0.456866979598999,"z":0.09594668447971344,"w":0.865470826625824},"size":12.932568550109864,"orthographic":false}